examples/__init__.py
examples/change_servo_id.py
examples/continuous_reading.py
examples/list_ports.py
examples/phase_control.py
examples/position_control.py
examples/read_voltage.py
examples/set_middle_position.py
examples/teleoperation.py
examples/torque_control.py
scservo_sdk/__init__.py
scservo_sdk/group_sync_read.py
scservo_sdk/group_sync_write.py
scservo_sdk/hls.py
scservo_sdk/port_handler.py
scservo_sdk/protocol_packet_handler.py
scservo_sdk/scscl.py
scservo_sdk/scservo_def.py
scservo_sdk/sms_sts.py
vassar_feetech_servo_sdk/__init__.py
vassar_feetech_servo_sdk/controller.py
vassar_feetech_servo_sdk/exceptions.py
vassar_feetech_servo_sdk-1.5.0.dist-info/licenses/LICENSE
vassar_feetech_servo_sdk-1.5.0.dist-info/METADATA
vassar_feetech_servo_sdk-1.5.0.dist-info/WHEEL
vassar_feetech_servo_sdk-1.5.0.dist-info/top_level.txt
vassar_feetech_servo_sdk-1.5.0.dist-info/RECORD
