Metadata-Version: 2.4
Name: vassar-feetech-servo-sdk
Version: 1.5.0
Summary: Vassar Robotics' Python SDK for Feetech servo control
Author-email: Vassar Robotics <hello@vassarrobotics.com>
Maintainer-email: Vassar Robotics <hello@vassarrobotics.com>
License: MIT
Project-URL: Homepage, https://github.com/vassar-robotics/feetech-servo-sdk
Project-URL: Repository, https://github.com/vassar-robotics/feetech-servo-sdk
Project-URL: Issues, https://github.com/vassar-robotics/feetech-servo-sdk/issues
Keywords: robotics,servo,feetech,serial,hardware,sts,hls,control
Classifier: Development Status :: 3 - Alpha
Classifier: Intended Audience :: Developers
Classifier: Intended Audience :: Science/Research
Classifier: License :: OSI Approved :: MIT License
Classifier: Operating System :: OS Independent
Classifier: Programming Language :: Python :: 3
Classifier: Programming Language :: Python :: 3.7
Classifier: Programming Language :: Python :: 3.8
Classifier: Programming Language :: Python :: 3.9
Classifier: Programming Language :: Python :: 3.10
Classifier: Programming Language :: Python :: 3.11
Classifier: Topic :: Scientific/Engineering
Classifier: Topic :: Software Development :: Libraries :: Python Modules
Requires-Python: >=3.7
License-File: LICENSE
Requires-Dist: pyserial>=3.5
Provides-Extra: dev
Requires-Dist: pytest>=7.0; extra == "dev"
Requires-Dist: pytest-cov>=4.0; extra == "dev"
Requires-Dist: black>=22.0; extra == "dev"
Requires-Dist: flake8>=5.0; extra == "dev"
Requires-Dist: mypy>=0.990; extra == "dev"
Requires-Dist: build>=0.9; extra == "dev"
Requires-Dist: twine>=4.0; extra == "dev"
Dynamic: license-file
